{
  "description": "Uptracks and traverses, transitions and descents \u2013 backcountry travel is not linear. Output, temperatures, and conditions shift, and you need to stay comfortable through it all. Created to meet these realities, the Proton Hybrid\u2019s Coreloft\u2122 Compact insulation and Fortius Air 50 outer balance warmth, airflow, and vapour transfer. GORE-TEX INFINIUM\u2122 at the yoke and hood delivers zonal windproof protection and helps shed light snow and sleet. Versatile, comfortable \u2013 this is a go-to backcountry piece.",
  "img_hrefs": [
    "https://vpo.ca/images/product/large/350462.jpg"
  ],
  "name": "Arcteryx Proton Hybrid Hoody - Mens",
  "price_cents": null,
  "specs": [],
  "url": "https://vpo.ca/product/350462/proton-hybrid-hoody-mens"
}