{
  "description": "The polo is an essential. Work, travel, everyday life \u2013 it goes everywhere you go. The Captive Polo builds on the classic with a cleaner fit, performance fabrics, and a refined look that expands its range. Lightweight, stretchy and breathable, the DryTech\u2122 fabric blends organically-grown cotton\u2019s cool, airy comfort and polyester\u2019s moisture management performance to make the Captive a go-to for active city commutes, weekend travel, and relaxed summer days.<br><br>Updated with organically grown cotton content.",
  "img_hrefs": [
    "https://vpo.ca/images/product/large/342329.jpg"
  ],
  "name": "Arcteryx Captive Polo - Mens",
  "price_cents": null,
  "specs": [],
  "url": "https://vpo.ca/product/342329/captive-polo-mens"
}