{
  "description": "Strap into Chillos Sport by Chaco. Designed for the unwind, these ultra-light sport sandals are perfect footwear for all manners of relaxation. The EVA construction means they float in water and are marshmallow soft underfoot. Engineered with Chaco\u2019s contoured LUVSEAT\u2122 arch-support that promotes healthy alignment, the corrective footbeds are accepted by the APMA (American Podiatric Medical Association) and feel fantastic after long runs, hikes, and workouts. Perfect for traveling, before and after the gym, the yoga studio, or just hanging poolside or fireside. Featuring Chaco\u2019s iconic Z/Strap adjustment with cinch buckle and secure heel strap. Vegan.",
  "img_hrefs": [
    "https://vpo.ca/images/product/large/338431.jpg"
  ],
  "name": "Chaco Chillos Sport - Mens",
  "price_cents": null,
  "specs": [],
  "url": "https://vpo.ca/product/338431/chillos-sport-mens"
}