{
  "description": "The Canyonland collection is the ultimate in land-to-water versatility and protection. Made to go where you go \u2013 from land to lake and back again \u2013 this lightweight, breathable, always-ready sneaker includes our removable LUVSEAT\u2122 arch support. Two types of traction are designed to give you grip on land and in water, while the outsole and protective mesh give you the versatility to quickly move between the two. Super quick drying to keep your feet comfortable, this shoe is designed to trek (or dive) into adventure.",
  "img_hrefs": [
    "https://vpo.ca/images/product/large/349746.jpg"
  ],
  "name": "Chaco Canyonland - Mens",
  "price_cents": null,
  "specs": [],
  "url": "https://vpo.ca/product/349746/canyonland-mens"
}