{
  "description": "Icebreaker's versatile merino wool Tech Lite II Short Sleeve Tee provides comfort, breathability and odor-resistance for just about any adventure you can think of. This tech tee features a retro inspired print of a moon lit trail in Queenstown, New Zealand.",
  "img_hrefs": [
    "https://vpo.ca/images/product/large/340037.jpg"
  ],
  "name": "Icebreaker Tech Lite II SS Tee - Trailhead - Mens",
  "price_cents": 800000,
  "specs": [],
  "url": "https://vpo.ca/product/340037/tech-lite-ii-ss-tee-trailhead-mens"
}