{
  "description": "The first mountaineering shoe featuring CE Certification for professional use. Super Ice Evo GTX satisfies all requirements and even more.<br><br>Suitable for classic routes, ice climbing and mixed terrains on high altitude. it is ideal for classical routes, glaciers, ice cascades and high altitude mixed rough terrains.<br><br>Exclusive antistatic construction, which transfer electrical shocks to the ground, thanks to a matel cable running along the upper and reaching the sole block.<br><br>Top quality Perwanger\u00ae leather upper and full rubber rand for increased protection.<br><br>Primaloft\u00ae lining to keep your feet warm and dry during the activity.<br><br>Secure closure and easy motion thanks to the extremely functional lacing system.<br><br>Smart PU midsole for maximum technicality in action and exclusive Anatomical Heel Technology to protect the heel and keep it in the right position.<br><br>Automatic crampons compatible.",
  "img_hrefs": [
    "https://vpo.ca/images/product/large/350538.jpg"
  ],
  "name": "Kayland - R.O.I. Recreation Outfitters Inc. Super Ice Evo GTX - Mens",
  "price_cents": null,
  "specs": [],
  "url": "https://vpo.ca/product/350538/super-ice-evo-gtx-mens"
}