{
  "description": "Engineered for the perfect fit, enjoy multi-season performance with K\u00dcHL\u2019s all-new REBEL\u2122 Men's Jacket. Fully insulated and fitted with soft flannel lining, you'll experience lightweight warmth and ultimate comfort when the chill sets in. The tough, abrasion-resistant exterior looks cotton-like but repels water like a synthetic. ? Three zippered pockets provide secure storage.",
  "img_hrefs": [
    "https://vpo.ca/images/product/large/337774.jpg"
  ],
  "name": "Kuhl Rebel Insulated Jacket - Mens",
  "price_cents": null,
  "specs": [],
  "url": "https://vpo.ca/product/337774/rebel-insulated-jacket-mens"
}