{
  "description": "They tweaked the designs of proven technology from years past to produce the Boulder X. Additional padding underfoot for long approaches and uber sticky rubber add deluxe comfort and performance. The Vibram\u00ae Idro-Grip compound stays sticky on every type of rock even when wet. The all-leather upper and sticky rubber toe rands offer durable protection. Ideal protection and performance built for the rigors and abuse of the mountains.",
  "img_hrefs": [
    "https://vpo.ca/images/product/large/259180.jpg"
  ],
  "name": "La Sportiva Boulder X - Mens",
  "price_cents": 1699500,
  "specs": [],
  "url": "https://vpo.ca/product/259180/boulder-x-mens"
}