{
  "description": "The TX2 EVO is a lightweight approach shoe that stows easily and is now designed with an easily re-soleable outsole. Enhanced support and sticky rubber keep you sure-footed in the mountains, while the one piece knit upper optimizes drainage and breathability. C2\u2122 ComboCord loops around the heel platform to allow easy pairing and storage in a pack.",
  "img_hrefs": [
    "https://vpo.ca/images/product/large/343186.jpg"
  ],
  "name": "La Sportiva TX2 EVO - Mens",
  "price_cents": 1799500,
  "specs": [],
  "url": "https://vpo.ca/product/343186/tx2-evo-mens"
}