{
  "description": "Saentis Pro WP Men. The stylish winter sneaker. Thanks to the direct interaction between the lacing and Basefit technology, this shoe provides excellent support and prevents blisters from forming. The Michelin OCX Compound ensures an excellent grip, while Dry Technology prevents moisture penetration. The winter sneaker comes with a soft shell upper material with a sock-like fit for increased comfort and a distinctive look.",
  "img_hrefs": [
    "https://vpo.ca/images/product/large/330974.jpg"
  ],
  "name": "Mammut Saentis Pro WP - Mens",
  "price_cents": 1880000,
  "specs": [],
  "url": "https://vpo.ca/product/330974/saentis-pro-wp-mens"
}