{
  "description": "With these stylish climbing pants from the Hueco family, you\u2019ll look good on your way to the climbing gym too. The resistant and abrasion-proof fabric makes the Hueco Cuffed Pants particularly robust. The elasticated material ensures maximum comfort. A drawstring allows you to adjust the pants to ensure a perfect fit. The front pocket on the right is ideal for storing your smartphone and there is also a zippered pocket on the back for your keys.",
  "img_hrefs": [
    "https://vpo.ca/images/product/large/343356.jpg"
  ],
  "name": "Mammut Hueco Cuffed Pants, Reg - Mens",
  "price_cents": null,
  "specs": [],
  "url": "https://vpo.ca/product/343356/hueco-cuffed-pants-reg-mens"
}