{
  "description": "Drop into the white room wearing the Men's Torgon Winter Jacket. Marmot MemBrain\u00ae waterproof/breathable fabric and 100% seam taping keep you dry in miles of fresh powder, while wind-resistant PrimaLoft\u00ae Black Insulation ECO offers warmth without weight. Heat-releasing PitZips cool you down when you work up a sweat. The helmet-compatible hood, fixed powder skirt, inner thumbholes, and VELCRO\u00ae wrist cuffs provide extra coverage from the elements. Stow ski gear in multiple zippered pockets.",
  "img_hrefs": [
    "https://vpo.ca/images/product/large/330466.jpg"
  ],
  "name": "Marmot Torgon Jacket - Mens",
  "price_cents": null,
  "specs": [],
  "url": "https://vpo.ca/product/330466/torgon-jacket-mens"
}