{
  "description": "Wise asses, step this way. Because this graphic tee (practically) has your name on it. Makes for a great gift too for that certain someone who always has to have the last word...<br><br>Speaking of words, there's a word we love around here: Fair. And this tee was made in a Fair Trade Certified\u2122 factory which means it empowers workers while protecting the environment too.",
  "img_hrefs": [
    "https://vpo.ca/images/product/large/336509.jpg"
  ],
  "name": "Prana Wise Ass Journeyman 2 - Slim - Mens",
  "price_cents": null,
  "specs": [],
  "url": "https://vpo.ca/product/336509/wise-ass-journeyman-2-slim-mens"
}