{
  "description": "Unsure of what the day\u2019s mission has in store? Reach for the Rush Mid GTX, our brand new, do-it-all trail shoe. The Rush Mid GTX features the same innovative Freedome\u2122 IKS\u2122 outsole as it\u2019s trail running sibling, the Rush, providing confidence-inspiring traction and stability for whatever the day has in store. The all-synthetic upper is light and nimble while still providing dynamic support, and offers waterproof-breathable protection via a GORE-TEX\u00ae Extended Comfort lining.",
  "img_hrefs": [
    "https://vpo.ca/images/product/large/330472.jpg"
  ],
  "name": "Scarpa Rush Mid GTX - Mens",
  "price_cents": null,
  "specs": [],
  "url": "https://vpo.ca/product/330472/rush-mid-gtx-mens"
}