{
  "description": "Their 100% Merino wool base layers are a wardrobe essential for every explorer, but this men's top is fashionable enough to wear out on the town, too. The side seams wrap to the front for a slim, body-enhancing fit. And the ribbed hoodie construction adds texture and style \u2014 perfect for happy hours and happier adventures.",
  "img_hrefs": [
    "https://vpo.ca/images/product/large/349621.jpg"
  ],
  "name": "Smartwool Classic Thermal Merino Base Layer Rib Hoodie - Mens",
  "price_cents": null,
  "specs": [],
  "url": "https://vpo.ca/product/349621/classic-thermal-merino-base-layer-rib-hoodie-mens"
}