{
  "description": "Merino Sport 150 fabric helps with breathability, temperature regulation, and odor control through responsibly sourced Merino wool while offering the quicker dry times of polyester. their Men\u2019s Merino Sport 150 go far. feel good.\u2122 Spokes Short Sleeve tee is designed with a fit that gives you room to move, as well as thoughtful seam construction that helps minimize chafing and increases comfort. Whether you pop it on for a Saturday with the fam or for a workout in the park, you\u2019ll get to enjoy this tee\u2019s softness and comfort.",
  "img_hrefs": [
    "https://vpo.ca/images/product/large/344698.jpg"
  ],
  "name": "Smartwool Merino Sport 150 Go Far, Feel Good Spokes SS Graphic Tee - Mens",
  "price_cents": null,
  "specs": [],
  "url": "https://vpo.ca/product/344698/merino-sport-150-go-far-feel-good-spokes-ss-graphic-tee-mens"
}