{
  "description": "Constructed with the outdoor enthusiast in mind, this men's \u00bc zip pullover is made of a Merino wool and recycled polyester blend that offers odor control, temperature regulation, and durability. Its underarm and back mesh panels ensure breathability, and it sports functional touches such as reflective elements and thoughtful seam construction. With this long-sleeved top on, you\u2019ll feel great in your cool- to warm-weather activities.",
  "img_hrefs": [
    "https://vpo.ca/images/product/large/343806.jpg"
  ],
  "name": "Smartwool Merino Sport (150) LS 1/4 Zip - Mens",
  "price_cents": null,
  "specs": [],
  "url": "https://vpo.ca/product/343806/merino-sport-150-ls-14-zip-mens"
}