{
  "description": "This casual minimalist shoe offers nature lovers a breathable, sustainable slip-on shoe with a true barefoot feel. Made from a hemp / poly blend and designed to slip on as a shoe or fold back as a clog, the CVT Hemp is both durable and comfortable.",
  "img_hrefs": [
    "https://vpo.ca/images/product/large/319938.jpg"
  ],
  "name": "Vibram Five Fingers CVT - Hemp - Khaki - Mens",
  "price_cents": 1599500,
  "specs": [],
  "url": "https://vpo.ca/product/319938/cvt-hemp-khaki-mens"
}